extpy/__init__.py
extpy-0.1.6.dist-info/METADATA
extpy-0.1.6.dist-info/WHEEL
extpy-0.1.6.dist-info/top_level.txt
extpy-0.1.6.dist-info/RECORD
