Metadata-Version: 2.1
Name: extpy
Version: 0.1.6
Summary: 自用基础扩展库
Home-page: https://vip.kingdee.com/people/zuiqingquan-2147424412
Author: ilamy
Author-email: xethan@qq.com
Requires-Dist: qrcode
Requires-Dist: pillow
